llama_index/readers/feishu_wiki/__init__.py
llama_index/readers/feishu_wiki/base.py
llama_index_readers_feishu_wiki-0.3.0.dist-info/METADATA
llama_index_readers_feishu_wiki-0.3.0.dist-info/WHEEL
llama_index_readers_feishu_wiki-0.3.0.dist-info/RECORD
